mochi_coco/__init__.py
mochi_coco/chat_controller.py
mochi_coco/cli.py
mochi_coco/py.typed
mochi_coco/user_prompt.py
mochi_coco/chat/__init__.py
mochi_coco/chat/session.py
mochi_coco/commands/__init__.py
mochi_coco/commands/command_processor.py
mochi_coco/constants/__init__.py
mochi_coco/controllers/__init__.py
mochi_coco/controllers/command_result_handler.py
mochi_coco/controllers/session_controller.py
mochi_coco/ollama/__init__.py
mochi_coco/ollama/async_client.py
mochi_coco/ollama/client.py
mochi_coco/rendering/__init__.py
mochi_coco/rendering/custom_markdown.py
mochi_coco/rendering/interrupt_handler.py
mochi_coco/rendering/markdown_renderer.py
mochi_coco/rendering/themes.py
mochi_coco/rendering/tool_aware_renderer.py
mochi_coco/services/__init__.py
mochi_coco/services/background_service_manager.py
mochi_coco/services/context_window_service.py
mochi_coco/services/renderer_manager.py
mochi_coco/services/session_creation_service.py
mochi_coco/services/session_creation_types.py
mochi_coco/services/session_manager.py
mochi_coco/services/session_setup_helper.py
mochi_coco/services/summarization_service.py
mochi_coco/services/summary_model_manager.py
mochi_coco/services/system_prompt_service.py
mochi_coco/services/user_preference_service.py
mochi_coco/tools/__init__.py
mochi_coco/tools/config.py
mochi_coco/tools/discovery_service.py
mochi_coco/tools/execution_service.py
mochi_coco/tools/schema_service.py
mochi_coco/ui/__init__.py
mochi_coco/ui/chat_interface.py
mochi_coco/ui/chat_ui_orchestrator.py
mochi_coco/ui/menu.py
mochi_coco/ui/menu_display.py
mochi_coco/ui/model_menu_handler.py
mochi_coco/ui/preference_collection_ui.py
mochi_coco/ui/session_creation_ui.py
mochi_coco/ui/system_prompt_menu_handler.py
mochi_coco/ui/tool_confirmation_ui.py
mochi_coco/ui/tool_selection_ui.py
mochi_coco/ui/user_interaction.py
mochi_coco/utils/__init__.py
mochi_coco/utils/chat_helpers.py
mochi_coco/utils/version.py
mochi_coco-0.6.1.dist-info/METADATA
mochi_coco-0.6.1.dist-info/WHEEL
mochi_coco-0.6.1.dist-info/entry_points.txt
mochi_coco-0.6.1.dist-info/licenses/LICENSE
mochi_coco-0.6.1.dist-info/RECORD
