Metadata-Version: 2.4
Name: mochi-coco
Version: 0.6.1
Summary: A beautiful, feature-rich CLI chat application for interacting with LLMs via Ollama with streaming responses, session persistence, markdown rendering and tool support.
Author-email: Lennart Pollvogt <lennartpollvogt@protonmail.com>
License-File: LICENSE
Requires-Python: >=3.10
Requires-Dist: ollama-instructor>=1.1.0
Requires-Dist: ollama>=0.5.3
Requires-Dist: prompt-toolkit>=3.0.52
Requires-Dist: rich>=13.0.0
Requires-Dist: ruff>=0.12.10
Requires-Dist: typer>=0.16.1
